vector_search/__init__.py
vector_search/__main__.py
vector_search/api/__init__.py
vector_search/api/routes/__init__.py
vector_search/api/routes/index.py
vector_search/api/schemas.py
vector_search/version-config.yaml
vector_search-0.0.1.dist-info/METADATA
vector_search-0.0.1.dist-info/WHEEL
vector_search-0.0.1.dist-info/entry_points.txt
vector_search-0.0.1.dist-info/RECORD
